<?xml version="1.0" encoding="UTF-8"?>
<entity-engine-xml>
    <PortletPortletCategory portalPortletId="ApInvoicesDueSoon" portletCategoryId="ACCOUNTING" lastUpdatedStamp="2015-06-18 14:49:58.117" lastUpdatedTxStamp="2015-06-18 14:49:58.096" createdStamp="2015-06-18 14:49:58.117" createdTxStamp="2015-06-18 14:49:58.096"/>
    <PortletPortletCategory portalPortletId="ApPastDueInvoices" portletCategoryId="ACCOUNTING" lastUpdatedStamp="2015-06-18 14:49:58.116" lastUpdatedTxStamp="2015-06-18 14:49:58.096" createdStamp="2015-06-18 14:49:58.116" createdTxStamp="2015-06-18 14:49:58.096"/>
    <PortletPortletCategory portalPortletId="ArInvoicesDueSoon" portletCategoryId="ACCOUNTING" lastUpdatedStamp="2015-06-18 14:49:58.109" lastUpdatedTxStamp="2015-06-18 14:49:58.096" createdStamp="2015-06-18 14:49:58.109" createdTxStamp="2015-06-18 14:49:58.096"/>
    <PortletPortletCategory portalPortletId="ArPastDueInvoices" portletCategoryId="ACCOUNTING" lastUpdatedStamp="2015-06-18 14:49:58.108" lastUpdatedTxStamp="2015-06-18 14:49:58.096" createdStamp="2015-06-18 14:49:58.108" createdTxStamp="2015-06-18 14:49:58.096"/>
    <PortletPortletCategory portalPortletId="Attributes" portletCategoryId="PARTY_PROFILE" lastUpdatedStamp="2015-06-18 14:49:54.52" lastUpdatedTxStamp="2015-06-18 14:49:54.513" createdStamp="2015-06-18 14:49:54.52" createdTxStamp="2015-06-18 14:49:54.513"/>
    <PortletPortletCategory portalPortletId="AvsSettings" portletCategoryId="PARTY_PROFILE" lastUpdatedStamp="2015-06-18 14:49:54.524" lastUpdatedTxStamp="2015-06-18 14:49:54.513" createdStamp="2015-06-18 14:49:54.524" createdTxStamp="2015-06-18 14:49:54.513"/>
    <PortletPortletCategory portalPortletId="BestSellingProducts" portletCategoryId="PRODUCTS" lastUpdatedStamp="2015-06-18 14:49:55.975" lastUpdatedTxStamp="2015-06-18 14:49:55.972" createdStamp="2015-06-18 14:49:55.975" createdTxStamp="2015-06-18 14:49:55.972"/>
    <PortletPortletCategory portalPortletId="Calendar" portletCategoryId="EVENTSTASKS" lastUpdatedStamp="2015-06-18 14:49:55.435" lastUpdatedTxStamp="2015-06-18 14:49:55.432" createdStamp="2015-06-18 14:49:55.435" createdTxStamp="2015-06-18 14:49:55.432"/>
    <PortletPortletCategory portalPortletId="contact" portletCategoryId="PARTY_PROFILE" lastUpdatedStamp="2015-06-18 14:49:54.544" lastUpdatedTxStamp="2015-06-18 14:49:54.513" createdStamp="2015-06-18 14:49:54.544" createdTxStamp="2015-06-18 14:49:54.513"/>
    <PortletPortletCategory portalPortletId="Content" portletCategoryId="PARTY_PROFILE" lastUpdatedStamp="2015-06-18 14:49:54.526" lastUpdatedTxStamp="2015-06-18 14:49:54.513" createdStamp="2015-06-18 14:49:54.526" createdTxStamp="2015-06-18 14:49:54.513"/>
    <PortletPortletCategory portalPortletId="FindGenericEntity" portletCategoryId="GENERIC_PORTLET" lastUpdatedStamp="2015-06-18 14:49:53.903" lastUpdatedTxStamp="2015-06-18 14:49:53.893" createdStamp="2015-06-18 14:49:53.903" createdTxStamp="2015-06-18 14:49:53.893"/>
    <PortletPortletCategory portalPortletId="GenericPortalPage" portletCategoryId="GENERIC_PORTLET" lastUpdatedStamp="2015-06-18 14:49:53.9" lastUpdatedTxStamp="2015-06-18 14:49:53.893" createdStamp="2015-06-18 14:49:53.9" createdTxStamp="2015-06-18 14:49:53.893"/>
    <PortletPortletCategory portalPortletId="GenericScreenlet" portletCategoryId="GENERIC_PORTLET" lastUpdatedStamp="2015-06-18 14:49:53.907" lastUpdatedTxStamp="2015-06-18 14:49:53.893" createdStamp="2015-06-18 14:49:53.907" createdTxStamp="2015-06-18 14:49:53.893"/>
    <PortletPortletCategory portalPortletId="GenericScreenletAjax" portletCategoryId="GENERIC_PORTLET" lastUpdatedStamp="2015-06-18 14:49:53.909" lastUpdatedTxStamp="2015-06-18 14:49:53.893" createdStamp="2015-06-18 14:49:53.909" createdTxStamp="2015-06-18 14:49:53.893"/>
    <PortletPortletCategory portalPortletId="GricScltAjaxWithMenu" portletCategoryId="GENERIC_PORTLET" lastUpdatedStamp="2015-06-18 14:49:53.912" lastUpdatedTxStamp="2015-06-18 14:49:53.893" createdStamp="2015-06-18 14:49:53.912" createdTxStamp="2015-06-18 14:49:53.893"/>
    <PortletPortletCategory portalPortletId="INCOM_CUST_REQUESTS" portletCategoryId="CUST_REQUEST" lastUpdatedStamp="2015-06-18 14:49:58.522" lastUpdatedTxStamp="2015-06-18 14:49:58.516" createdStamp="2015-06-18 14:49:58.522" createdTxStamp="2015-06-18 14:49:58.516"/>
    <PortletPortletCategory portalPortletId="ListCustomerInvoices" portletCategoryId="ACCOUNTING" lastUpdatedStamp="2015-06-18 14:49:58.1" lastUpdatedTxStamp="2015-06-18 14:49:58.096" createdStamp="2015-06-18 14:49:58.1" createdTxStamp="2015-06-18 14:49:58.096"/>
    <PortletPortletCategory portalPortletId="ListCustomerOrders" portletCategoryId="ORDERMGR" lastUpdatedStamp="2015-06-18 14:49:58.53" lastUpdatedTxStamp="2015-06-18 14:49:58.516" createdStamp="2015-06-18 14:49:58.53" createdTxStamp="2015-06-18 14:49:58.516"/>
    <PortletPortletCategory portalPortletId="ListCustRequests" portletCategoryId="LIST_CUSTOMER" lastUpdatedStamp="2015-06-18 14:49:58.527" lastUpdatedTxStamp="2015-06-18 14:49:58.516" createdStamp="2015-06-18 14:49:58.527" createdTxStamp="2015-06-18 14:49:58.516"/>
    <PortletPortletCategory portalPortletId="ListCustReturns" portletCategoryId="CUST_ORDERS" lastUpdatedStamp="2015-06-18 14:49:58.56" lastUpdatedTxStamp="2015-06-18 14:49:58.516" createdStamp="2015-06-18 14:49:58.56" createdTxStamp="2015-06-18 14:49:58.516"/>
    <PortletPortletCategory portalPortletId="ListPayments" portletCategoryId="ACCOUNTING" lastUpdatedStamp="2015-06-18 14:49:58.126" lastUpdatedTxStamp="2015-06-18 14:49:58.096" createdStamp="2015-06-18 14:49:58.126" createdTxStamp="2015-06-18 14:49:58.096"/>
    <PortletPortletCategory portalPortletId="ListPurchaseOrders" portletCategoryId="ORDERMGR" lastUpdatedStamp="2015-06-18 14:49:58.557" lastUpdatedTxStamp="2015-06-18 14:49:58.516" createdStamp="2015-06-18 14:49:58.557" createdTxStamp="2015-06-18 14:49:58.516"/>
    <PortletPortletCategory portalPortletId="ListSalesOrders" portletCategoryId="ORDERMGR" lastUpdatedStamp="2015-06-18 14:49:58.532" lastUpdatedTxStamp="2015-06-18 14:49:58.516" createdStamp="2015-06-18 14:49:58.532" createdTxStamp="2015-06-18 14:49:58.516"/>
    <PortletPortletCategory portalPortletId="ListSupplierInvoices" portletCategoryId="ACCOUNTING" lastUpdatedStamp="2015-06-18 14:49:58.124" lastUpdatedTxStamp="2015-06-18 14:49:58.096" createdStamp="2015-06-18 14:49:58.124" createdTxStamp="2015-06-18 14:49:58.096"/>
    <PortletPortletCategory portalPortletId="LoyaltyPoints" portletCategoryId="PARTY_PROFILE" lastUpdatedStamp="2015-06-18 14:49:54.528" lastUpdatedTxStamp="2015-06-18 14:49:54.513" createdStamp="2015-06-18 14:49:54.528" createdTxStamp="2015-06-18 14:49:54.513"/>
    <PortletPortletCategory portalPortletId="MyCommunications" portletCategoryId="COMMUNICATIONS" lastUpdatedStamp="2015-06-18 14:49:54.553" lastUpdatedTxStamp="2015-06-18 14:49:54.513" createdStamp="2015-06-18 14:49:54.553" createdTxStamp="2015-06-18 14:49:54.513"/>
    <PortletPortletCategory portalPortletId="myLeave" portletCategoryId="HUMANRES" lastUpdatedStamp="2015-06-18 14:49:58.273" lastUpdatedTxStamp="2015-06-18 14:49:58.269" createdStamp="2015-06-18 14:49:58.273" createdTxStamp="2015-06-18 14:49:58.269"/>
    <PortletPortletCategory portalPortletId="MYTASKSPARTY" portletCategoryId="PARTY_PROFILE" lastUpdatedStamp="2015-06-18 14:49:54.53" lastUpdatedTxStamp="2015-06-18 14:49:54.513" createdStamp="2015-06-18 14:49:54.53" createdTxStamp="2015-06-18 14:49:54.513"/>
    <PortletPortletCategory portalPortletId="MyTrainings" portletCategoryId="HUMANRES" lastUpdatedStamp="2015-06-18 14:49:58.276" lastUpdatedTxStamp="2015-06-18 14:49:58.269" createdStamp="2015-06-18 14:49:58.276" createdTxStamp="2015-06-18 14:49:58.269"/>
    <PortletPortletCategory portalPortletId="Notes" portletCategoryId="PARTY_PROFILE" lastUpdatedStamp="2015-06-18 14:49:54.532" lastUpdatedTxStamp="2015-06-18 14:49:54.513" createdStamp="2015-06-18 14:49:54.532" createdTxStamp="2015-06-18 14:49:54.513"/>
    <PortletPortletCategory portalPortletId="OpenOrderItems" portletCategoryId="REPORT" lastUpdatedStamp="2015-06-18 14:49:58.545" lastUpdatedTxStamp="2015-06-18 14:49:58.516" createdStamp="2015-06-18 14:49:58.545" createdTxStamp="2015-06-18 14:49:58.516"/>
    <PortletPortletCategory portalPortletId="party" portletCategoryId="PARTY_PROFILE" lastUpdatedStamp="2015-06-18 14:49:54.518" lastUpdatedTxStamp="2015-06-18 14:49:54.513" createdStamp="2015-06-18 14:49:54.518" createdTxStamp="2015-06-18 14:49:54.513"/>
    <PortletPortletCategory portalPortletId="PartyIdentifications" portletCategoryId="PARTY_PROFILE" lastUpdatedStamp="2015-06-18 14:49:54.522" lastUpdatedTxStamp="2015-06-18 14:49:54.513" createdStamp="2015-06-18 14:49:54.522" createdTxStamp="2015-06-18 14:49:54.513"/>
    <PortletPortletCategory portalPortletId="partyLoggedIn" portletCategoryId="PARTY_PROFILE" lastUpdatedStamp="2015-06-18 14:49:54.55" lastUpdatedTxStamp="2015-06-18 14:49:54.513" createdStamp="2015-06-18 14:49:54.55" createdTxStamp="2015-06-18 14:49:54.513"/>
    <PortletPortletCategory portalPortletId="partyRelAccounts" portletCategoryId="PARTY_PROFILE" lastUpdatedStamp="2015-06-18 14:49:54.548" lastUpdatedTxStamp="2015-06-18 14:49:54.513" createdStamp="2015-06-18 14:49:54.548" createdTxStamp="2015-06-18 14:49:54.513"/>
    <PortletPortletCategory portalPortletId="partyRelContacts" portletCategoryId="PARTY_PROFILE" lastUpdatedStamp="2015-06-18 14:49:54.546" lastUpdatedTxStamp="2015-06-18 14:49:54.513" createdStamp="2015-06-18 14:49:54.546" createdTxStamp="2015-06-18 14:49:54.513"/>
    <PortletPortletCategory portalPortletId="PaymentMethods" portletCategoryId="PARTY_PROFILE" lastUpdatedStamp="2015-06-18 14:49:54.534" lastUpdatedTxStamp="2015-06-18 14:49:54.513" createdStamp="2015-06-18 14:49:54.534" createdTxStamp="2015-06-18 14:49:54.513"/>
    <PortletPortletCategory portalPortletId="PrdStoreFacilityMgmt" portletCategoryId="PRODUCTSTORE" lastUpdatedStamp="2015-06-18 14:49:55.978" lastUpdatedTxStamp="2015-06-18 14:49:55.972" createdStamp="2015-06-18 14:49:55.978" createdTxStamp="2015-06-18 14:49:55.972"/>
    <PortletPortletCategory portalPortletId="ProductStores" portletCategoryId="PARTY_PROFILE" lastUpdatedStamp="2015-06-18 14:49:54.542" lastUpdatedTxStamp="2015-06-18 14:49:54.513" createdStamp="2015-06-18 14:49:54.542" createdTxStamp="2015-06-18 14:49:54.513"/>
    <PortletPortletCategory portalPortletId="PurchasesByOrg" portletCategoryId="REPORT" lastUpdatedStamp="2015-06-18 14:49:58.548" lastUpdatedTxStamp="2015-06-18 14:49:58.516" createdStamp="2015-06-18 14:49:58.548" createdTxStamp="2015-06-18 14:49:58.516"/>
    <PortletPortletCategory portalPortletId="PurchasesByProduct" portletCategoryId="REPORT" lastUpdatedStamp="2015-06-18 14:49:58.551" lastUpdatedTxStamp="2015-06-18 14:49:58.516" createdStamp="2015-06-18 14:49:58.551" createdTxStamp="2015-06-18 14:49:58.516"/>
    <PortletPortletCategory portalPortletId="PurchByPaymMeth" portletCategoryId="REPORT" lastUpdatedStamp="2015-06-18 14:49:58.554" lastUpdatedTxStamp="2015-06-18 14:49:58.516" createdStamp="2015-06-18 14:49:58.554" createdTxStamp="2015-06-18 14:49:58.516"/>
    <PortletPortletCategory portalPortletId="SalesByStore" portletCategoryId="REPORT" lastUpdatedStamp="2015-06-18 14:49:58.542" lastUpdatedTxStamp="2015-06-18 14:49:58.516" createdStamp="2015-06-18 14:49:58.542" createdTxStamp="2015-06-18 14:49:58.516"/>
    <PortletPortletCategory portalPortletId="ShipperAccount" portletCategoryId="PARTY_PROFILE" lastUpdatedStamp="2015-06-18 14:49:54.536" lastUpdatedTxStamp="2015-06-18 14:49:54.513" createdStamp="2015-06-18 14:49:54.536" createdTxStamp="2015-06-18 14:49:54.513"/>
    <PortletPortletCategory portalPortletId="showContent" portletCategoryId="CONTENT" lastUpdatedStamp="2015-06-18 14:49:55.301" lastUpdatedTxStamp="2015-06-18 14:49:55.298" createdStamp="2015-06-18 14:49:55.301" createdTxStamp="2015-06-18 14:49:55.298"/>
    <PortletPortletCategory portalPortletId="SystemInfoNotes" portletCategoryId="SYSTEMINFO" lastUpdatedStamp="2015-06-18 14:49:58.887" lastUpdatedTxStamp="2015-06-18 14:49:58.884" createdStamp="2015-06-18 14:49:58.887" createdTxStamp="2015-06-18 14:49:58.884"/>
    <PortletPortletCategory portalPortletId="SystemInfoStatus" portletCategoryId="SYSTEMINFO" lastUpdatedStamp="2015-06-18 14:49:58.892" lastUpdatedTxStamp="2015-06-18 14:49:58.884" createdStamp="2015-06-18 14:49:58.892" createdTxStamp="2015-06-18 14:49:58.884"/>
    <PortletPortletCategory portalPortletId="UserLogin" portletCategoryId="PARTY_PROFILE" lastUpdatedStamp="2015-06-18 14:49:54.538" lastUpdatedTxStamp="2015-06-18 14:49:54.513" createdStamp="2015-06-18 14:49:54.538" createdTxStamp="2015-06-18 14:49:54.513"/>
    <PortletPortletCategory portalPortletId="ViewCustRequest" portletCategoryId="CUST_REQUEST" lastUpdatedStamp="2015-06-18 14:49:58.524" lastUpdatedTxStamp="2015-06-18 14:49:58.516" createdStamp="2015-06-18 14:49:58.524" createdTxStamp="2015-06-18 14:49:58.516"/>
    <PortletPortletCategory portalPortletId="Visits" portletCategoryId="PARTY_PROFILE" lastUpdatedStamp="2015-06-18 14:49:54.54" lastUpdatedTxStamp="2015-06-18 14:49:54.513" createdStamp="2015-06-18 14:49:54.54" createdTxStamp="2015-06-18 14:49:54.513"/>
</entity-engine-xml>
